{
  "id": "ryHbtfPgkem5Aw2",
  "unique_key": "https://twitter.com/irshadk70832751",
  "order_no": null,
  "handled_at": "2025-08-06 08:00:42.848064+00:00",
  "request": {
    "url": "https://twitter.com/IrshadK70832751",
    "method": "GET",
    "headers": {},
    "payload": null,
    "user_data": {
      "__crawlee": {
        "state": 5
      }
    },
    "retry_count": 3,
    "no_retry": false,
    "loaded_url": null,
    "handled_at": "2025-08-06 08:00:42.848064+00:00",
    "unique_key": "https://twitter.com/irshadk70832751",
    "id": "ryHbtfPgkem5Aw2"
  }
}